helpful_site-0.1.0.dist-info/RECORD
helpful_site-0.1.0.dist-info/top_level.txt
helpful_site-0.1.0.dist-info/pbr.json
helpful_site-0.1.0.dist-info/DESCRIPTION.rst
helpful_site-0.1.0.dist-info/METADATA
helpful_site-0.1.0.dist-info/metadata.json
helpful_site-0.1.0.dist-info/entry_points.txt
helpful_site-0.1.0.dist-info/WHEEL
helpful_site/__init__.py
helpful_site/cli.py
helpful_site/__main__.py
