Metadata-Version: 2.0
Name: helpful-site
Version: 0.1.0
Summary: Beautifully simple static site generator in Python
Home-page: https://github.com/g4b1nagy/helpful-site
Author: Gabi Nagy
Author-email: gabrian.nagy@gmail.com
License: Unlicense
Platform: UNKNOWN
Classifier: Development Status :: 5 - Production/Stable
Classifier: Intended Audience :: Developers
Classifier: License :: OSI Approved :: BSD License
Classifier: Operating System :: Unix
Classifier: Operating System :: POSIX
Classifier: Operating System :: Microsoft :: Windows
Classifier: Programming Language :: Python
Classifier: Programming Language :: Python :: 2.6
Classifier: Programming Language :: Python :: 2.7
Classifier: Programming Language :: Python :: 3
Classifier: Programming Language :: Python :: 3.3
Classifier: Programming Language :: Python :: 3.4
Classifier: Programming Language :: Python :: Implementation :: CPython
Classifier: Programming Language :: Python :: Implementation :: PyPy
Classifier: Topic :: Utilities
Requires-Dist: Jinja2
Requires-Dist: Markdown
Requires-Dist: MarkupSafe
Requires-Dist: PyYAML
Requires-Dist: Pygments
Requires-Dist: Unidecode
Requires-Dist: argparse
Requires-Dist: click
Requires-Dist: crammit
Requires-Dist: cssmin
Requires-Dist: envoy
Requires-Dist: ply
Requires-Dist: python-slugify
Requires-Dist: slimit
